{"32":{"w":9,"h":0,"space":true},"33":{"w":4,"h":44},"35":{"w":20,"h":44},"39":{"w":4,"h":44},"40":{"w":8,"h":44},"41":{"w":8,"h":44},"42":{"w":14,"h":44},"43":{"w":19,"h":44},"44":{"w":7,"h":44},"45":{"w":9,"h":44},"46":{"w":4,"h":44},"48":{"w":16,"h":44},"49":{"w":15,"h":44},"50":{"w":18,"h":44},"51":{"w":17,"h":44},"52":{"w":19,"h":44},"53":{"w":21,"h":44},"54":{"w":17,"h":44},"55":{"w":22,"h":44},"56":{"w":16,"h":44},"57":{"w":15,"h":44},"58":{"w":4,"h":44},"63":{"w":10,"h":44},"64":{"w":19,"h":44},"65":{"w":23,"h":44},"66":{"w":21,"h":44},"67":{"w":18,"h":44},"68":{"w":19,"h":44},"69":{"w":16,"h":44},"70":{"w":16,"h":44},"71":{"w":20,"h":44},"72":{"w":22,"h":44},"73":{"w":4,"h":44},"74":{"w":7,"h":44},"75":{"w":21,"h":44},"76":{"w":18,"h":44},"77":{"w":24,"h":44},"78":{"w":19,"h":44},"79":{"w":20,"h":44},"80":{"w":19,"h":44},"81":{"w":23,"h":44},"82":{"w":24,"h":44},"83":{"w":22,"h":44},"84":{"w":20,"h":44},"85":{"w":22,"h":44},"86":{"w":19,"h":44},"87":{"w":29,"h":44},"88":{"w":21,"h":44},"89":{"w":21,"h":44},"90":{"w":26,"h":44},"97":{"w":12,"h":44},"98":{"w":11,"h":44},"99":{"w":12,"h":44},"100":{"w":14,"h":44},"101":{"w":10,"h":44},"102":{"w":15,"h":44},"103":{"w":15,"h":44},"104":{"w":13,"h":44},"105":{"w":9,"h":44},"106":{"w":7,"h":44},"107":{"w":17,"h":44},"108":{"w":9,"h":44},"109":{"w":26,"h":44},"110":{"w":19,"h":44},"111":{"w":11,"h":44},"112":{"w":14,"h":44},"113":{"w":18,"h":44},"114":{"w":12,"h":44},"115":{"w":13,"h":44},"116":{"w":12,"h":44},"117":{"w":17,"h":44},"118":{"w":16,"h":44},"119":{"w":21,"h":44},"120":{"w":16,"h":44},"121":{"w":16,"h":44},"122":{"w":17,"h":44},"9829":{"w":11,"h":44}}